{"main":{"id":197909,"updated_at":"2024-11-15 14:10:07","product_name":"ملایر و تویسرکان","stock":30000,"min_sale_price":250000,"min_sale_amount":50,"description":"گردو ملایر و تویسرکان از بهترین نوع درختان گردو را دارا هستند،گردو از نظر چرب و پوست کاغذی بودن بسیار مورد توجه قرار میگیرد و برای مصارف خانگی از جمله گردو فسنجانی بسیار مورد استقبال قرار میگیرد،بسیار مهم است که گردو از کجا تهیه و به دست مصرف کننده برسد.\r\nما قابلیت تامین گردو و آنچه شما نیازدارید را داریم.<hr\/>برای اطلاع از قیمت روز ملایر و تویسرکان و خرید مستقیم پیام ارسال کنید.<hr\/>میزان تازه بودن و زمان تولید این محصول : تازه چیده شده<hr\/>نوع بسته بندی و وزن ارائه شده توسط فروشنده برای این محصول : آنطور که مصرف کننده نیاز دارد<hr\/>مقدار موجودی آماده فروش برای این محصول : 30000 کیلوگرم<hr\/>حداقل مقدار فروش این محصول توسط فروشنده در یک معامله : 50 کیلوگرم<hr\/>","myuser_id":1070201,"sub_category_id":54,"province_name":"همدان","province_id":30,"city_name":" ملایر","city_id":425,"sub_category_name":"گردو","unit":"کیلوگرم","is_elevated":0,"category_name":"خشکبار","category_id":45,"is_old":false},"user_info":{"id":1070201,"user_name":"bp3fz","first_name":"حسن","last_name":"فرداد","active_pakage_type":2,"created_at":"2024-09-18 21:22:05","is_verified":1},"profile_info":[],"photos":[{"file_path":"https:\/\/product-thumbnails.s3.ir-thr-at1.arvanstorage.com\/web-1727554038989-676994164-N8JDSuGUb7vn9Bj1WJZn8mzjRklAcWtuAl98nhqg.jpeg"}]}