{
    "main": {
        "id": 207668,
        "updated_at": "2024-11-16 09:53:13",
        "product_name": "عسل ارگانیک",
        "stock": 2000000,
        "min_sale_price": 200000,
        "min_sale_amount": 10,
        "description": "بهترین گردو و عسل دماوند عسل اویشن ارگانیک فروش جزئ و عمده ارسال به تمام کشور<hr\/>برای اطلاع از قیمت روز گردو و عسل ارگانیک  و خرید مستقیم پیام ارسال کنید.<hr\/>میزان مرغوبیت و کیفیت ظاهری محصول ارائه شده : کیفیت عالی <hr\/>شرایط پرداخت پول در معامله طبق نظر فروشنده برای فروش این محصول : جزئ و عمده<hr\/>میزان تازه بودن و زمان تولید این محصول : محصول دماوند تازه و با کیفیت<hr\/>مقدار موجودی آماده فروش برای این محصول : 2000000 لیتر<hr\/>حداقل مقدار فروش این محصول توسط فروشنده در یک معامله : 10 لیتر<hr\/>",
        "myuser_id": 1148737,
        "sub_category_id": 60,
        "province_name": "تهران",
        "province_id": 8,
        "city_name": " دماوند",
        "city_id": 88,
        "sub_category_name": "عسل",
        "unit": "کیلوگرم",
        "is_elevated": 0,
        "category_name": "دامپروری",
        "category_id": 47,
        "is_old": false
    },
    "user_info": {
        "id": 1148737,
        "user_name": "c5vl",
        "first_name": "محمدرضا",
        "last_name": "روستایی",
        "active_pakage_type": 0,
        "created_at": "2024-11-13 20:05:27",
        "is_verified": 0
    },
    "profile_info": [],
    "photos": [
        {
            "file_path": "https:\/\/product-thumbnails.s3.ir-thr-at1.arvanstorage.com\/web-1731738218401-458398198-E0E7Keg0jmnO0p4qkW9hr86m9YjTKcxrop4e4SwR.jpeg"
        }
    ]
}