{"main":{"id":188093,"updated_at":"2024-11-14 09:17:05","product_name":"کنجد ارده ای","stock":20000,"min_sale_price":125000,"min_sale_amount":700,"description":"شرکت کیان تجارت دکاموند، شرکت بازرگانی جام سحر\r\nفروشنده کنجد، نارگیل ، کاکائو\r\nبهترین و مطمئن ترین محل خرید محصول از جهت کیفیت و تضمین بار\r\nتمام بارها مجوزهای رسمی دارند\r\nتنوع محصول برای لوازم قنادی ها، تولیدکنندگان و کارگاه های تولیدی\r\nبازرگانی جام سحر\r\nبرای اطلاع از قیمت روز سفید هندی و خرید مستقیم پیام ارسال کنید.<hr\/>برای اطلاع از قیمت روز کنجد ارده ای و خرید مستقیم پیام ارسال کنید.<hr\/>میزان مرغوبیت و کیفیت ظاهری محصول ارائه شده : با ضمانت کیفیت<hr\/>شرایط پرداخت پول در معامله طبق نظر فروشنده برای فروش این محصول : با حداقل سفارش<hr\/>مقدار موجودی آماده فروش برای این محصول : 20000 کیلوگرم<hr\/>حداقل مقدار فروش این محصول توسط فروشنده در یک معامله : 250 کیلوگرم<hr\/>","myuser_id":398044,"sub_category_id":70,"province_name":"تهران","province_id":8,"city_name":" تهران","city_id":87,"sub_category_name":"کنجد","unit":"کیلوگرم","is_elevated":0,"category_name":"غلات","category_id":42,"is_old":false},"user_info":{"id":398044,"user_name":"n46185y","first_name":"شرکت","last_name":"كيان تجارت دكاموند","active_pakage_type":2,"created_at":"2022-12-11 11:29:45","is_verified":1},"profile_info":[],"photos":[{"file_path":"https:\/\/product-thumbnails.s3.ir-thr-at1.arvanstorage.com\/web-1721635796269-819675832-zL5Wi0UFllDd1qmfeDh5pWGCbkg8Ies2OXVBaHFI.jpeg"}]}