{"main":{"id":190247,"updated_at":"2024-11-14 11:23:24","product_name":"نخود دوخان","stock":30000,"min_sale_price":83000,"min_sale_amount":30000,"description":"نخود دوخان کرمانشاه  صادراتی درجه یک \r\nجهت موجود بودن کالا و استعلام قیمت تماس بگیرید<hr\/>برای اطلاع از قیمت روز نخود دوخان و خرید مستقیم پیام ارسال کنید.<hr\/>شرایط پرداخت پول در معامله طبق نظر فروشنده برای فروش این محصول : فروش به صورت نقد<hr\/>مقدار موجودی آماده فروش برای این محصول : 30000 کیلوگرم<hr\/>حداقل مقدار فروش این محصول توسط فروشنده در یک معامله : 30000 کیلوگرم<hr\/>","myuser_id":856071,"sub_category_id":74,"province_name":"كرمانشاه","province_id":22,"city_name":" کرمانشاه","city_id":247,"sub_category_name":"نخود","unit":"کیلوگرم","is_elevated":0,"category_name":"حبوبات","category_id":71,"is_old":false},"user_info":{"id":856071,"user_name":"71x155","first_name":"بهمن","last_name":"چلیپا","active_pakage_type":1,"created_at":"2024-03-09 00:01:36","is_verified":1},"profile_info":[],"photos":[{"file_path":"https:\/\/product-thumbnails.s3.ir-thr-at1.arvanstorage.com\/web-1722782824303-899409085-qGQeLjjQQeeehIwyLn70rXXOde8cTLj5q8XbrQv0.jpeg"}]}