{"main":{"id":207257,"updated_at":"2024-11-14 09:34:07","product_name":"ویژه ، نول ، ممتاز","stock":20000000,"min_sale_price":2000,"min_sale_amount":2000,"description":"با سلام و احترام \r\nفروش خیارشور ویژه نول ممتاز بصورت دبه ای و حلب بفروش می‌رسد \r\nبا نازلترین قیمت از یک تولید کننده با خیال راحت خرید کنید \r\nفروش محصول بصورت نقد و چکی می‌باشد درضمن بستگی به نظر فروشنده میباشد<hr\/>برای اطلاع از قیمت روز ویژه ، نول ، ممتاز  و خرید مستقیم پیام ارسال کنید.<hr\/>میزان مرغوبیت و کیفیت ظاهری محصول ارائه شده : ماندگاری بالا و کاملا ارگانیک و بهداشتی<hr\/>مزیت این محصول نسبت به محصولات مشابه : محتویات داخل دبه 8کیلو خالص خیار، آب اشامیدنی، سیر ، فلفل، ترخون ، و شوید میباشد<hr\/>مقدار موجودی آماده فروش برای این محصول : 20000000 کیلوگرم<hr\/>حداقل مقدار فروش این محصول توسط فروشنده در یک معامله : 2000 کیلوگرم<hr\/>","myuser_id":1148812,"sub_category_id":105,"province_name":"همدان","province_id":30,"city_name":" همدان","city_id":427,"sub_category_name":"خیارشور","unit":"کیلوگرم","is_elevated":0,"category_name":"کنسانتره و کنسرو","category_id":81,"is_old":false},"user_info":{"id":1148812,"user_name":"ou18mp3wx10z","first_name":"علی","last_name":"عابدی","active_pakage_type":0,"created_at":"2024-11-13 20:50:48","is_verified":0},"profile_info":[],"photos":[{"file_path":"https:\/\/product-thumbnails.s3.ir-thr-at1.arvanstorage.com\/web-1731519026624-834855603-h9i7WagTQ7qgN5mhedxvS4CUMT7D28zUOf5qrrAR.jpeg"}]}