{
    "main": {
        "id": 205751,
        "updated_at": "2024-11-16 14:35:59",
        "product_name": "مکنده جوشی تک 1.5 اسب 3000 دور مستقیم",
        "stock": 700,
        "min_sale_price": 9219000,
        "min_sale_amount": 1,
        "description": "لوازم جانبی مکنده: با الکتروموتور تکفاز ایرانی با الکتروموتور سه فاز ایرانی بدون الکتروموتور\r\n\r\nفرم مکنده: 3S32P9\r\n\r\nقطر پروانه (سانتی متر): 32\r\n\r\nدبی (مترمکعب در ساعت):  3050\r\n\r\nتوان ورودی: 1.5HP - 1.1KW\r\n\r\nفشار (پاسکال): 1800\r\n\r\nقطر دهانه مکش (سانتی متر): 20<hr\/>برای اطلاع از قیمت روز مکنده جوشی تک 1.5 اسب 3000 دور مستقیم و خرید مستقیم پیام ارسال کنید.<hr\/>مزیت این محصول نسبت به محصولات مشابه : برای این مدل مکنده باید سفارش بزارین تا براتون تولید بشه<hr\/>مقدار موجودی آماده فروش برای این محصول : 700 عدد<hr\/>حداقل مقدار فروش این محصول توسط فروشنده در یک معامله : 1 عدد<hr\/>",
        "myuser_id": 1053777,
        "sub_category_id": 668,
        "province_name": "تهران",
        "province_id": 8,
        "city_name": " تهران",
        "city_id": 87,
        "sub_category_name": "سایر تجهیزات صنعتی",
        "unit": "عدد",
        "is_elevated": 0,
        "category_name": "تجهیزات صنعتی",
        "category_id": 614,
        "is_old": false
    },
    "user_info": {
        "id": 1053777,
        "user_name": "20ykfw",
        "first_name": "شرکت",
        "last_name": "کالا صنعتی",
        "active_pakage_type": 2,
        "created_at": "2024-09-05 09:05:22",
        "is_verified": 1
    },
    "profile_info": [],
    "photos": [
        {
            "file_path": "https:\/\/product-thumbnails.s3.ir-thr-at1.arvanstorage.com\/web-1730966210070-621718399-dHw5bHyws99Mm2wth2PaZ2R5cYGncHVIC0SRuTSm.jpeg"
        }
    ]
}